mcp_hackernews/__init__.py
mcp_hackernews/main.py
mcp_hackernews-1.1.0.dist-info/METADATA
mcp_hackernews-1.1.0.dist-info/WHEEL
mcp_hackernews-1.1.0.dist-info/entry_points.txt
mcp_hackernews-1.1.0.dist-info/top_level.txt
mcp_hackernews-1.1.0.dist-info/RECORD
