Metadata-Version: 2.4
Name: mcp-hackernews
Version: 1.1.0
Summary: MCP server for Hacker News search (top stories)
Author: YinTokey
License: MIT
Keywords: mcp,model-context-protocol,hackernews,mcp-name: io.github.YinTokey/mcp_hackernews
Classifier: Programming Language :: Python :: 3
Classifier: Programming Language :: Python :: 3.12
Classifier: Intended Audience :: Developers
Classifier: Topic :: Software Development :: Libraries
Classifier: License :: OSI Approved :: MIT License
Requires-Python: >=3.12
Requires-Dist: mcp[cli]>=1.14.1
Requires-Dist: httpx>=0.27.0
